david_seekdb_mcp_server-0.0.3.dist-info/licenses/LICENSE
seekdb_mcp/__init__.py
seekdb_mcp/__main__.py
seekdb_mcp/server.py
tests/__init__.py
tests/test_server.py
david_seekdb_mcp_server-0.0.3.dist-info/METADATA
david_seekdb_mcp_server-0.0.3.dist-info/WHEEL
david_seekdb_mcp_server-0.0.3.dist-info/entry_points.txt
david_seekdb_mcp_server-0.0.3.dist-info/top_level.txt
david_seekdb_mcp_server-0.0.3.dist-info/RECORD
