Metadata-Version: 2.4
Name: david-seekdb-mcp-server
Version: 0.0.3
Summary: A Model Context Protocol (MCP) server that enables interaction with seekdb database. This server allows AI assistants to perform vector operations, manage collections, execute SQL queries and leverage AI functions through a controlled interface, making database exploration and analysis safer and more structured.
License:                                  Apache License
Keywords: seekdb,mcp
Classifier: Development Status :: 3 - Alpha
Classifier: Programming Language :: Python :: 3
Classifier: Programming Language :: Python :: 3.11
Requires-Python: <3.13,>=3.11
License-File: LICENSE
Requires-Dist: mcp>=1.13.1
Requires-Dist: fastmcp>=2.12.0
Requires-Dist: mysql-connector-python>=9.1.0
Requires-Dist: SQLAlchemy>=2.0.32
Requires-Dist: beautifulsoup4>=4.13.5
Requires-Dist: pydantic>=2.11.7
Requires-Dist: python-dotenv>=1.1.1
Requires-Dist: certifi>=2022.12.7
Requires-Dist: pyseekdb>=1.0.0b2
Provides-Extra: dev
Requires-Dist: ruff>=0.1.0; extra == "dev"
Requires-Dist: pytest>=7.0.0; extra == "dev"
Dynamic: license-file
